{
  "category": "design",
  "label": "设计系统",
  "icon": "🎨",
  "updated": "2026-05-26T00:14:54.372Z",
  "count": 1,
  "repos": [
    {
      "fullName": "rohitg00/ai-engineering-from-scratch",
      "owner": "rohitg00",
      "name": "ai-engineering-from-scratch",
      "description": "Learn it. Build it. Ship it for others.",
      "url": "https://github.com/rohitg00/ai-engineering-from-scratch",
      "avatarUrl": "https://github.com/rohitg00.png",
      "stars": 18493,
      "forks": 3141,
      "todayStars": 0,
      "language": "Python",
      "topics": []
    }
  ],
  "error": null
}