{
  "category": "mobile",
  "label": "移动开发",
  "icon": "📱",
  "updated": "2026-06-06T17:48:17.143Z",
  "count": 1,
  "repos": [
    {
      "fullName": "CopilotKit/CopilotKit",
      "owner": "CopilotKit",
      "name": "CopilotKit",
      "description": "The Frontend Stack for Agents &amp; Generative UI. React, Angular, Mobile, Slack, and more. Makers of the AG-UI Protocol",
      "url": "https://github.com/CopilotKit/CopilotKit",
      "avatarUrl": "https://github.com/CopilotKit.png",
      "stars": 33082,
      "forks": 4225,
      "todayStars": 0,
      "language": "TypeScript",
      "topics": []
    }
  ],
  "error": null
}